zenq/__init__.py
zenq/api/__init__.py
zenq/api/config.py
zenq/api/endpoints.py
zenq/api/prepare_db.py
zenq/api/tables.py
zenq/clvmodels/__init__.py
zenq/clvmodels/pareto.py
zenq/datapreparation/__init__.py
zenq/datapreparation/preparation.py
zenq/logger/__init__.py
zenq/logger/logger.py
zenq/visualizations/__init__.py
zenq/visualizations/plot.py
zenq-0.1.0.dist-info/AUTHORS.rst
zenq-0.1.0.dist-info/LICENSE
zenq-0.1.0.dist-info/METADATA
zenq-0.1.0.dist-info/WHEEL
zenq-0.1.0.dist-info/entry_points.txt
zenq-0.1.0.dist-info/top_level.txt
zenq-0.1.0.dist-info/RECORD
